sphinx_charts/__init__.py
sphinx_charts/charts.css
sphinx_charts/charts.js
sphinx_charts/charts.py
sphinx_charts/extensions/MathJax.js
sphinx_charts-0.2.0.dist-info/LICENSE
sphinx_charts-0.2.0.dist-info/WHEEL
sphinx_charts-0.2.0.dist-info/METADATA
sphinx_charts-0.2.0.dist-info/RECORD
