Metadata-Version: 2.1
Name: sphinx-charts
Version: 0.2.0
Summary: Interactive charts, graphs and figures for Sphinx HTML docs.
Home-page: https://github.com/thclark/sphinx-charts
License: MIT
Keywords: sphinx,charts,python,docs,plotly,graphs,figures,plot,d3
Author: thclark
Requires-Python: >=3.7,<4.0
Classifier: Development Status :: 4 - Beta
Classifier: Environment :: Plugins
Classifier: Environment :: Web Environment
Classifier: Framework :: Sphinx :: Extension
Classifier: Intended Audience :: Developers
Classifier: License :: OSI Approved :: MIT License
Classifier: Natural Language :: English
Classifier: Operating System :: OS Independent
Classifier: Programming Language :: Python :: 3
Classifier: Programming Language :: Python :: 3.10
Classifier: Programming Language :: Python :: 3.6
Classifier: Programming Language :: Python :: 3.7
Classifier: Programming Language :: Python :: 3.8
Classifier: Programming Language :: Python :: 3.9
Classifier: Topic :: Documentation
Classifier: Topic :: Documentation :: Sphinx
Classifier: Topic :: Software Development :: Documentation
Classifier: Topic :: Text Processing
Classifier: Topic :: Utilities
Provides-Extra: docs
Requires-Dist: sphinx (>=4,<5); extra == "docs"
Requires-Dist: sphinx-math-dollar (==1.2.0); extra == "docs"
Requires-Dist: sphinx-rtd-theme (==1.0.0); extra == "docs"
Requires-Dist: sphinx-tabs (==3.2.0); extra == "docs"
Project-URL: Repository, https://github.com/thclark/sphinx-charts
